dailyprogrammer/__init__.py
dailyprogrammer/dp.py
dailyprogrammer-1.0.dist-info/DESCRIPTION.rst
dailyprogrammer-1.0.dist-info/METADATA
dailyprogrammer-1.0.dist-info/RECORD
dailyprogrammer-1.0.dist-info/WHEEL
dailyprogrammer-1.0.dist-info/entry_points.txt
dailyprogrammer-1.0.dist-info/metadata.json
dailyprogrammer-1.0.dist-info/top_level.txt
